[
  {
    "Id": "58cd24ff0bde4ca1d2ff9a7b",
    "name": "Event1",
    "desc": "Perkins",
    "date": "Sat Feb 02 1985 19:07:17 GMT+0200 (Jerusalem Standard Time)",
    "lon":"35.771959",
    "lat":"31.77777"

  },
  {
    "Id": "58cd24ff8242ebd874dc8f22",
    "name": "Event2",
    "desc": "Hess",
    "date": "Thu Jun 01 1972 16:31:19 GMT+0300 (Jerusalem Daylight Time)",
    "lon":"34.771959",
    "lat":"32.77777"
  },
  {
    "Id": "58cd24ff590fb887aac4a972",
    "name": "Event3",
    "desc": "Jacobs",
    "date": "Fri Sep 28 2001 19:49:26 GMT+0300 (Jerusalem Daylight Time)",
    "lon":"33.771959",
    "lat":"30.77777"
  },
  {
    "Id": "58cd24ff67e1a745a22addbe",
    "name": "Event4",
    "desc": "Burris",
    "date": "Wed Jan 09 1985 13:34:32 GMT+0200 (Jerusalem Standard Time)",
    "lon":"32.771959",
    "lat":"29.77777"
  },
  {
    "Id": "58cd24ff804547b9423d4684",
    "name": "Event5",
    "desc": "Dale",
    "date": "Sun Jun 19 1977 03:46:29 GMT+0300 (Jerusalem Daylight Time)",
    "lon":"31.771959",
    "lat":"28.77777"
  },
  {
    "Id": "58cd24ff8e30d9eb4212a4ac",
    "name": "Event6",
    "desc": "Haney",
    "date": "Fri Nov 24 1972 01:01:36 GMT+0200 (Jerusalem Standard Time)",
    "lon":"30.771959",
    "lat":"27.77777"
  }
]
